archx/__init__.py
archx/main.py
archx/architecture/__init__.py
archx/architecture/architecture.py
archx/event/__init__.py
archx/event/event.py
archx/interface/__init__.py
archx/interface/interface.py
archx/interface/cacti7/__init__.py
archx/interface/cacti7/cacti7.py
archx/interface/cacti7/ddr4.cfg
archx/interface/cacti7/sram.cfg
archx/interface/cacti7/include/cacti7/README
archx/interface/cacti7/include/cacti7/TSV.cc
archx/interface/cacti7/include/cacti7/TSV.h
archx/interface/cacti7/include/cacti7/Ucache.cc
archx/interface/cacti7/include/cacti7/Ucache.h
archx/interface/cacti7/include/cacti7/arbiter.cc
archx/interface/cacti7/include/cacti7/arbiter.h
archx/interface/cacti7/include/cacti7/area.cc
archx/interface/cacti7/include/cacti7/area.h
archx/interface/cacti7/include/cacti7/bank.cc
archx/interface/cacti7/include/cacti7/bank.h
archx/interface/cacti7/include/cacti7/basic_circuit.cc
archx/interface/cacti7/include/cacti7/basic_circuit.h
archx/interface/cacti7/include/cacti7/cacti
archx/interface/cacti7/include/cacti7/cacti.i
archx/interface/cacti7/include/cacti7/cacti.mk
archx/interface/cacti7/include/cacti7/cacti_interface.cc
archx/interface/cacti7/include/cacti7/cacti_interface.h
archx/interface/cacti7/include/cacti7/component.cc
archx/interface/cacti7/include/cacti7/component.h
archx/interface/cacti7/include/cacti7/const.h
archx/interface/cacti7/include/cacti7/contention.dat
archx/interface/cacti7/include/cacti7/crossbar.cc
archx/interface/cacti7/include/cacti7/crossbar.h
archx/interface/cacti7/include/cacti7/decoder.cc
archx/interface/cacti7/include/cacti7/decoder.h
archx/interface/cacti7/include/cacti7/extio.cc
archx/interface/cacti7/include/cacti7/extio.h
archx/interface/cacti7/include/cacti7/extio_technology.cc
archx/interface/cacti7/include/cacti7/extio_technology.h
archx/interface/cacti7/include/cacti7/htree2.cc
archx/interface/cacti7/include/cacti7/htree2.h
archx/interface/cacti7/include/cacti7/io.cc
archx/interface/cacti7/include/cacti7/io.h
archx-2025.8.9.dist-info/METADATA
archx-2025.8.9.dist-info/WHEEL
archx-2025.8.9.dist-info/entry_points.txt
archx-2025.8.9.dist-info/licenses/LICENSE
archx-2025.8.9.dist-info/RECORD
