Metadata-Version: 2.4
Name: archx
Version: 2025.8.9
Summary: A framework to explore the design space of hardware architecture.
Project-URL: Homepage, https://github.com/UnaryLab/archx
Project-URL: Issues, https://github.com/UnaryLab/archx/issues
Author-email: Di Wu <di.wu@ucf.edu>, Daniel Price <daniel.price@ucf.edu>, Tyler Goldsmith <tyler.goldsmith@ucf.edu>
License: MIT License
License-File: LICENSE
Classifier: Programming Language :: Python
Requires-Python: >=3.9
Requires-Dist: loguru
Requires-Dist: pyfiglet
Requires-Dist: pyyaml
Requires-Dist: yamlordereddictloader
